{
  "notes": [
    {
      "content": "Comprar presente para o aniversário da mãe na próxima semana",
      "id": "3",
      "title": "Lembrete de aniversário"
    },
    {
      "content": "Procurar receitas de pratos vegetarianos para experimentar",
      "id": "6",
      "title": "Novas receitas"
    },
    {
      "id": "8",
      "title": "Ideias para o blog",
      "content": "Escrever sobre dicas de viagem, revisar os últimos posts"
    },
    {
      "id": "10",
      "title": "Notas da aula",
      "content": "Revisar os slides da aula de história para o exame"
    },
    {
      "id": "13",
      "title": "Lembretes de saúde",
      "content": "Tomar vitaminas diárias, fazer 30 minutos de exercícios"
    },
    {
      "content": "Reservar hotel, comprar passagens, montar roteiro",
      "id": "14",
      "title": "Planos de viagem"
    },
    {
      "id": "15",
      "title": "Receita de bolo",
      "content": "Farinha, açúcar, ovos, chocolate, fermento"
    },
    {
      "content": "Novo celular, livro de receitas, ingressos para o concerto",
      "id": "16",
      "title": "Lista de desejos"
    },
    {
      "id": "19",
      "title": "Aniversário de casamento",
      "content": "Comprar presente e reservar mesa no restaurante"
    },
    {
      "id": "20",
      "title": "Notas de reunião",
      "content": "Discutir resultados do último trimestre, definir metas para o próximo"
    },
    {
      "id": "3bbc",
      "title": "Ideias para o projeto!",
      "content": "Enviar e-mail para o cliente, pesquisar novas tecnologias, reunir a equipe"
    },
    {
      "id": "e0e3",
      "content": "yrsfsdf",
      "title": "yrdyr"
    }
  ]
}